mcp_memory_system/__init__.py
mcp_memory_system/__main__.py
mcp_memory_system/server.py
mcp_memory_system/pyarmor_runtime_000000/__init__.py
mcp_memory_system/pyarmor_runtime_000000/darwin_universal/pyarmor_runtime.so
iflow_mcp_memory_system-0.1.4.dist-info/METADATA
iflow_mcp_memory_system-0.1.4.dist-info/WHEEL
iflow_mcp_memory_system-0.1.4.dist-info/entry_points.txt
iflow_mcp_memory_system-0.1.4.dist-info/licenses/LICENSE
iflow_mcp_memory_system-0.1.4.dist-info/RECORD
