Metadata-Version: 2.4
Name: iflow-mcp_memory-system
Version: 0.1.4
Summary: A Model Context Protocol server providing file system management tools with enhanced editing capabilities
Author: Memory System Team
License: MIT
License-File: LICENSE
Keywords: automation,file-system,llm,mcp,memory
Classifier: Development Status :: 4 - Beta
Classifier: Intended Audience :: Developers
Classifier: License :: OSI Approved :: MIT License
Classifier: Programming Language :: Python :: 3
Classifier: Programming Language :: Python :: 3.10
Classifier: Programming Language :: Python :: 3.11
Classifier: Programming Language :: Python :: 3.12
Requires-Python: ==3.12.7
Requires-Dist: langchain-core>=0.1.0
Requires-Dist: langchain-mcp-adapters>=0.1.0
Requires-Dist: mcp>=1.1.3
Requires-Dist: pydantic>=2.0.0
